atradebot/__init__.py
atradebot/auto.py
atradebot/main.py
atradebot/params.py
atradebot/data/__init__.py
atradebot/data/collect.py
atradebot/data/get_news.py
atradebot/data/llm_prompt.py
atradebot/data/yf_data.py
atradebot/strategies/__init__.py
atradebot/strategies/arima.py
atradebot/strategies/gpt.py
atradebot/strategies/llama3.py
atradebot/strategies/simple.py
atradebot/strategies/strategy.py
atradebot/trainer/__init__.py
atradebot/trainer/train_llama3.py
atradebot/utils/__init__.py
atradebot/utils/alpaca_trade.py
atradebot/utils/backtest.py
atradebot/utils/portfolio.py
atradebot/utils/search.py
atradebot/utils/ta.py
atradebot/utils/utils.py
atradebot-0.2.0.dist-info/METADATA
atradebot-0.2.0.dist-info/WHEEL
atradebot-0.2.0.dist-info/top_level.txt
atradebot-0.2.0.dist-info/RECORD
