Metadata-Version: 2.2
Name: atradebot
Version: 0.2.0
Summary: atradebot package
Author-email: AndreChang <andrechang67@gmail.com>
Keywords: algotrade,fintech,stocks
Classifier: Programming Language :: Python :: 3
Classifier: License :: OSI Approved :: MIT License
Classifier: Operating System :: OS Independent
Requires-Python: >=3.7
Requires-Dist: beautifulsoup4
Requires-Dist: bitsandbytes
Requires-Dist: datasets
Requires-Dist: huggingface_hub
Requires-Dist: matplotlib
Requires-Dist: nltk
Requires-Dist: numpy
Requires-Dist: pandas
Requires-Dist: peft
Requires-Dist: pytest
Requires-Dist: python_dateutil
Requires-Dist: PyYAML
Requires-Dist: scikit_learn
Requires-Dist: sentencepiece
Requires-Dist: setuptools
Requires-Dist: torch
Requires-Dist: transformers
Requires-Dist: yfinance
Requires-Dist: lxml_html_clean
Requires-Dist: trafilatura
Requires-Dist: finnhub-python
Requires-Dist: openai
Requires-Dist: sentence-transformers
Requires-Dist: PyPortfolioOpt
Requires-Dist: diskcache
Requires-Dist: statsmodels
Requires-Dist: pmdarima
Requires-Dist: gitpython
Requires-Dist: alpaca-py
